symcircuit/__init__.py
symcircuit/bode.py
symcircuit/plotting.py
symcircuit/spice.py
symcircuit/system.py
symcircuit-0.3.0.dist-info/licenses/LICENSE
symcircuit-0.3.0.dist-info/METADATA
symcircuit-0.3.0.dist-info/WHEEL
symcircuit-0.3.0.dist-info/top_level.txt
symcircuit-0.3.0.dist-info/RECORD
