Metadata-Version: 2.4
Name: SymCircuit
Version: 0.3.0
Summary: Symbolic electronic circuit analysis
Home-page: https://github.com/martok/py-symcircuit
Author: Martok
Author-email: martok@martoks-place.de
License: MIT
Project-URL: Bug Tracker, https://github.com/martok/py-symcircuit/issues
Classifier: Development Status :: 4 - Beta
Classifier: License :: OSI Approved :: MIT License
Classifier: Operating System :: OS Independent
Classifier: Intended Audience :: Science/Research
Classifier: Intended Audience :: Developers
Classifier: Topic :: Scientific/Engineering :: Mathematics
Classifier: Topic :: Scientific/Engineering :: Electronic Design Automation (EDA)
Requires-Python: >=3.6
License-File: LICENSE
Requires-Dist: sympy
Provides-Extra: ee
Requires-Dist: networkx; extra == "ee"
Requires-Dist: numpy; extra == "ee"
Requires-Dist: mplotkit; extra == "ee"
Dynamic: author
Dynamic: author-email
Dynamic: classifier
Dynamic: description
Dynamic: description-content-type
Dynamic: home-page
Dynamic: license
Dynamic: license-file
Dynamic: project-url
Dynamic: provides-extra
Dynamic: requires-dist
Dynamic: requires-python
Dynamic: summary
